dbt/adapters/dremio/__init__.py
dbt/adapters/dremio/__version__.py
dbt/adapters/dremio/column.py
dbt/adapters/dremio/connections.py
dbt/adapters/dremio/credentials.py
dbt/adapters/dremio/impl.py
dbt/adapters/dremio/relation.py
dbt/adapters/dremio/api/authentication.py
dbt/adapters/dremio/api/cursor.py
dbt/adapters/dremio/api/handle.py
dbt/adapters/dremio/api/parameters.py
dbt/adapters/dremio/api/rest/client.py
dbt/adapters/dremio/api/rest/error.py
dbt/adapters/dremio/api/rest/url_builder.py
dbt/adapters/dremio/api/rest/utils.py
dbt/adapters/dremio/api/rest/entities/__init__.py
dbt/adapters/dremio/api/rest/entities/reflection.py
dbt/include/dremio/__init__.py
dbt/include/dremio/dbt_project.yml
dbt/include/dremio/profile_template.yml
dbt/include/dremio/macros/adapters/apply_grants.sql
dbt/include/dremio/macros/adapters/columns.sql
dbt/include/dremio/macros/adapters/data_preparation.sql
dbt/include/dremio/macros/adapters/external_query.sql
dbt/include/dremio/macros/adapters/format.sql
dbt/include/dremio/macros/adapters/metadata.sql
dbt/include/dremio/macros/adapters/persist_docs.sql
dbt/include/dremio/macros/adapters/relation.sql
dbt/include/dremio/macros/adapters/snapshot.sql
dbt/include/dremio/macros/adapters/sources.sql
dbt/include/dremio/macros/adapters/timestamp.sql
dbt/include/dremio/macros/adapters/validate_sql.sql
dbt/include/dremio/macros/builtins/builtins.sql
dbt/include/dremio/macros/get_custom_name/get_custom_alias.sql
dbt/include/dremio/macros/get_custom_name/get_custom_database.sql
dbt/include/dremio/macros/get_custom_name/get_custom_schema.sql
dbt/include/dremio/macros/get_custom_name/is_datalake_node.sql
dbt/include/dremio/macros/materializations/can_clone_table.sql
dbt/include/dremio/macros/materializations/clone.sql
dbt/include/dremio/macros/materializations/helpers.sql
dbt/include/dremio/macros/materializations/twin_strategy.sql
dbt/include/dremio/macros/materializations/unit.sql
dbt/include/dremio/macros/materializations/incremental/incremental.sql
dbt_dremio-1.8.4.dist-info/licenses/LICENSE
dbt_dremio-1.8.4.dist-info/METADATA
dbt_dremio-1.8.4.dist-info/WHEEL
dbt_dremio-1.8.4.dist-info/top_level.txt
dbt_dremio-1.8.4.dist-info/RECORD
