Metadata-Version: 2.4
Name: dbt-dremio
Version: 1.8.4
Summary: The Dremio adapter plugin for dbt
Home-page: https://github.com/dremio/dbt-dremio
Author: Dremio
License: Apache Software License 2.0 (http://www.apache.org/licenses/LICENSE-2.0)
Classifier: License :: OSI Approved :: Apache Software License
Classifier: Operating System :: Microsoft :: Windows
Classifier: Operating System :: MacOS :: MacOS X
Classifier: Operating System :: POSIX :: Linux
Classifier: Programming Language :: Python :: 3.11
Requires-Python: >=3.8
License-File: LICENSE
Requires-Dist: dbt-core>=1.8
Requires-Dist: dbt-adapters<2.0.0,>=1.0.0
Requires-Dist: requests>=2.31.0
Dynamic: author
Dynamic: classifier
Dynamic: description
Dynamic: home-page
Dynamic: license
Dynamic: license-file
Dynamic: requires-dist
Dynamic: requires-python
Dynamic: summary
